sevensegdecoder.v
// sevensegdecoder.v
// Based off of sevenseghexdecoder.v from lab 4 

`timescale 1ns / 1ps 

module sevensegdecoder(Seg,Val); 
	output 	[0:6] Seg; 
	input 	[3:0] Val; 
	reg 	[0:6] Seg; 
	
	always @(Val)  
	begin 	
		case(Val) // 0 = On | 1 = Off
			4'h0: Seg = 7'b000_0001; 
			4'h1: Seg = 7'b100_1111; //      0
			4'h2: Seg = 7'b001_0010; //     ---
			4'h3: Seg = 7'b000_0110; // 5  |   |  1
			4'h4: Seg = 7'b100_1100; //     -6-
			4'h5: Seg = 7'b010_0100; // 4  |   |  2
			4'h6: Seg = 7'b010_0000; //     ---
			4'h7: Seg = 7'b000_1111; //      3
			4'h8: Seg = 7'b000_0000;
			4'h9: Seg = 7'b000_0100;
			default: Seg = 7'b000_0000;
		endcase
	end
endmodule

counter.v
// counter.v
// Based on count00to59.v

module counter(min,secmsd,seclsd,ten,clk,clr,en,up);
	output [3:0] min,secmsd,seclsd,ten;
	input  clk,clr,en,up;

	wire  upen,bken,mupen,mbken,minupen,minbken,lsden,msden,minen;
	
	count_to9 tenth(ten,clk,clr,en,up,upen,bken);
	count_to9 lsdig_second(seclsd,clk,clr,lsden,up,mupen,mbken);
	count_to5 msdig_second(secmsd,clk,clr,msden,up,minupen,minbken);
	count_to9 minute(min,clk,clr,minen,up, , );

	assign lsden = (clr && en) || upen || bken;
	assign msden = (clr && en) || mupen || mbken;
	assign minen = (clr && en) || minupen || minbken;
endmodule

// count_to9.v
// ctrl --> 1 - Minutes | 2 - Seconds | 3 - Tenths
module count_to9(cnt,clk,clr,en,up,upen,bken);
	output [3:0] cnt;
	output       upen, bken;
	input        clk, clr, en, up;

	reg    [3:0] cnt, ncnt;

	// Go to next count every posedge of the clock
	always @(posedge clk)
	begin
		if(en)
			if(clr)
				cnt <= 0;
			else
				cnt <= ncnt;
		else
			cnt <= cnt;
		
	end

	// Handle rollover
	always @(cnt or up)
	begin
		if(up)
			ncnt=(cnt==9) ? 0 : cnt+1;
		else
			ncnt=(cnt==0) ? 9 : cnt-1;
	end

	assign upen = (cnt==9) && up && en;
	assign bken = (cnt==0) && !up && en;
endmodule

// count_to5.v
module count_to5(cnt,clk,clr,en,up,upen,bken);
	output [3:0] cnt;
	output       upen, bken;
	input        clk, clr, en, up;

	reg    [3:0] cnt, ncnt;

	// Go to next count every posedge of the clock
	always @(posedge clk)
	begin
		if(en)
			if(clr)
				cnt <= 0;
			else
				cnt <= ncnt;
		else
			cnt <= cnt;
	end

	// Handle rollover
	always @(cnt or up)
	begin
		if(up)
			ncnt=(cnt==5) ? 0 : cnt+1;
		else
			ncnt=(cnt==0) ? 5 : cnt-1;
	end

	assign upen = (cnt==5) && up && en;
	assign bken = (cnt==0) && !up && en;
endmodule

Level1/stopwatch.v
`include "counter.v"
`include "sevensegdecoder.v"

module stopwatch(clk,en,up,reset,lap,seg1,seg2,seg3,seg4,d1,d2,d3,d4,dot);
	output [6:0] seg1, seg2, seg3, seg4;
	output [3:0] d1,d2,d3,d4; //d1 = minutes | d2d3 = seconds | d4 = tenths
	output dot;	
	input clk,en,up,reset,lap;
		
	counter count(.min(d1),.secmsd(d2),.seclsd(d3),.ten(d4),.clk(clk),
		.clr(reset),.en(en),.up(up));
		
	sevensegdecoder ssd1(.Seg(seg1),.Val(d1));
	sevensegdecoder ssd2(.Seg(seg2),.Val(d2));
	sevensegdecoder ssd3(.Seg(seg3),.Val(d3));
	sevensegdecoder ssd4(.Seg(seg4),.Val(d4));
	
endmodule

Level1/tb_stopwatch.v
// Test bench
`include "stopwatch.v"
`timescale 1ns / 1ns

module tb_stopwatch();
	wire [6:0] tseg1,tseg2,tseg3,tseg4;
	wire [3:0] td1, td2, td3, td4;
	wire	   tdot;
	reg        tclk, ten, tup, tclr, tlap;
        
	stopwatch   dut(tclk,ten,tup,tclr,tlap,tseg1,tseg2,tseg3,tseg4,td1,td2,td3,td4,tdot);

	initial
	begin
		$dumpfile("tb.vcd");
		$dumpvars(0,tb_stopwatch);
		tclk=0; tclr=1; ten=1; tup=1;
		#20000 $finish;
	end

	always
		#10 tclk = !tclk;

	initial 
	fork
		#50 tclr=0;
		#10100 ten = 0;
		#10125 tclr = 1;
		#10175 tclr = 0;
		#10200 ten = 1;
		#10300 tclr = 1;
		#10400 tclr = 0;
		#12000 tup = 0;
		#15000 tup = 1;
	join
endmodule

tb.vcd
$date
	Tue Apr 18 10:48:53 2017
$end
$version
	Icarus Verilog
$end
$timescale
	1ps
$end
$scope module tb_stopwatch $end
$var wire 4 ! td1 [3:0] $end
$var wire 4 " td2 [3:0] $end
$var wire 4 # td3 [3:0] $end
$var wire 4 $ td4 [3:0] $end
$var wire 1 % tdot $end
$var wire 7 & tseg1 [6:0] $end
$var wire 7 ' tseg2 [6:0] $end
$var wire 7 ( tseg3 [6:0] $end
$var wire 7 ) tseg4 [6:0] $end
$var reg 1 * tclk $end
$var reg 1 + tclr $end
$var reg 1 , ten $end
$var reg 1 - tlap $end
$var reg 1 . tup $end
$scope module dut $end
$var wire 1 / clk $end
$var wire 4 0 d1 [3:0] $end
$var wire 4 1 d2 [3:0] $end
$var wire 4 2 d3 [3:0] $end
$var wire 4 3 d4 [3:0] $end
$var wire 1 % dot $end
$var wire 1 4 en $end
$var wire 1 5 lap $end
$var wire 1 6 reset $end
$var wire 7 7 seg1 [6:0] $end
$var wire 7 8 seg2 [6:0] $end
$var wire 7 9 seg3 [6:0] $end
$var wire 7 : seg4 [6:0] $end
$var wire 1 ; up $end
$scope module count $end
$var wire 1 < bken $end
$var wire 1 / clk $end
$var wire 1 6 clr $end
$var wire 1 4 en $end
$var wire 1 = lsden $end
$var wire 1 > mbken $end
$var wire 4 ? min [3:0] $end
$var wire 1 @ minbken $end
$var wire 1 A minen $end
$var wire 1 B minupen $end
$var wire 1 C msden $end
$var wire 1 D mupen $end
$var wire 4 E seclsd [3:0] $end
$var wire 4 F secmsd [3:0] $end
$var wire 4 G ten [3:0] $end
$var wire 1 ; up $end
$var wire 1 H upen $end
$scope module tenth $end
$var wire 1 < bken $end
$var wire 1 / clk $end
$var wire 1 6 clr $end
$var wire 1 4 en $end
$var wire 1 ; up $end
$var wire 1 H upen $end
$var reg 4 I cnt [3:0] $end
$var reg 4 J ncnt [3:0] $end
$upscope $end
$scope module lsdig_second $end
$var wire 1 > bken $end
$var wire 1 / clk $end
$var wire 1 6 clr $end
$var wire 1 = en $end
$var wire 1 ; up $end
$var wire 1 D upen $end
$var reg 4 K cnt [3:0] $end
$var reg 4 L ncnt [3:0] $end
$upscope $end
$scope module msdig_second $end
$var wire 1 @ bken $end
$var wire 1 / clk $end
$var wire 1 6 clr $end
$var wire 1 C en $end
$var wire 1 ; up $end
$var wire 1 B upen $end
$var reg 4 M cnt [3:0] $end
$var reg 4 N ncnt [3:0] $end
$upscope $end
$scope module minute $end
$var wire 1 O bken $end
$var wire 1 / clk $end
$var wire 1 6 clr $end
$var wire 1 A en $end
$var wire 1 ; up $end
$var wire 1 P upen $end
$var reg 4 Q cnt [3:0] $end
$var reg 4 R ncnt [3:0] $end
$upscope $end
$upscope $end
$scope module ssd1 $end
$var wire 4 S Val [3:0] $end
$var reg 7 T Seg [0:6] $end
$upscope $end
$scope module ssd2 $end
$var wire 4 U Val [3:0] $end
$var reg 7 V Seg [0:6] $end
$upscope $end
$scope module ssd3 $end
$var wire 4 W Val [3:0] $end
$var reg 7 X Seg [0:6] $end
$upscope $end
$scope module ssd4 $end
$var wire 4 Y Val [3:0] $end
$var reg 7 Z Seg [0:6] $end
$upscope $end
$upscope $end
$upscope $end
$enddefinitions $end
#0
$dumpvars
bx Z
bx Y
bx X
bx W
bx V
bx U
bx T
bx S
bx R
bx Q
xP
0O
bx N
bx M
bx L
bx K
bx J
bx I
xH
bx G
bx F
bx E
xD
1C
xB
1A
0@
bx ?
0>
1=
0<
1;
bx :
bx 9
bx 8
bx 7
16
x5
14
bx 3
bx 2
bx 1
bx 0
0/
1.
x-
1,
1+
0*
bx )
bx (
bx '
bx &
z%
bx $
bx #
bx "
bx !
$end
#10000
0H
0D
0B
0P
b1 Z
b1 )
b1 :
b1 J
b1 X
b1 (
b1 9
b1 L
b1 V
b1 '
b1 8
b1 N
b1 T
b1 &
b1 7
b1 R
b0 I
b0 $
b0 3
b0 G
b0 Y
b0 K
b0 #
b0 2
b0 E
b0 W
b0 M
b0 "
b0 1
b0 F
b0 U
b0 Q
b0 !
b0 0
b0 ?
b0 S
1*
1/
#20000
0*
0/
#30000
1*
1/
#40000
0*
0/
#50000
b1001111 Z
b1001111 )
b1001111 :
b10 J
b1001111 X
b1001111 (
b1001111 9
b10 L
b1001111 V
b1001111 '
b1001111 8
b10 N
b1001111 T
b1001111 &
b1001111 7
b10 R
b1 I
b1 $
b1 3
b1 G
b1 Y
b1 K
b1 #
b1 2
b1 E
b1 W
b1 M
b1 "
b1 1
b1 F
b1 U
b1 Q
b1 !
b1 0
b1 ?
b1 S
0=
0C
0A
1*
1/
0+
06
#60000
0*
0/
#70000
b10010 Z
b10010 )
b10010 :
b11 J
b10 I
b10 $
b10 3
b10 G
b10 Y
1*
1/
#80000
0*
0/
#90000
b110 Z
b110 )
b110 :
b100 J
b11 I
b11 $
b11 3
b11 G
b11 Y
1*
1/
#100000
0*
0/
#110000
b1001100 Z
b1001100 )
b1001100 :
b101 J
b100 I
b100 $
b100 3
b100 G
b100 Y
1*
1/
#120000
0*
0/
#130000
b100100 Z
b100100 )
b100100 :
b110 J
b101 I
b101 $
b101 3
b101 G
b101 Y
1*
1/
#140000
0*
0/
#150000
b100000 Z
b100000 )
b100000 :
b111 J
b110 I
b110 $
b110 3
b110 G
b110 Y
1*
1/
#160000
0*
0/
#170000
b1111 Z
b1111 )
b1111 :
b1000 J
b111 I
b111 $
b111 3
b111 G
b111 Y
1*
1/
#180000
0*
0/
#190000
b0 Z
b0 )
b0 :
b1001 J
b1000 I
b1000 $
b1000 3
b1000 G
b1000 Y
1*
1/
#200000
0*
0/
#210000
1=
1H
b100 Z
b100 )
b100 :
b0 J
b1001 I
b1001 $
b1001 3
b1001 G
b1001 Y
1*
1/
#220000
0*
0/
#230000
0=
0H
b10010 X
b10010 (
b10010 9
b11 L
b1 Z
b1 )
b1 :
b1 J
b10 K
b10 #
b10 2
b10 E
b10 W
b0 I
b0 $
b0 3
b0 G
b0 Y
1*
1/
#240000
0*
0/
#250000
b1001111 Z
b1001111 )
b1001111 :
b10 J
b1 I
b1 $
b1 3
b1 G
b1 Y
1*
1/
#260000
0*
0/
#270000
b10010 Z
b10010 )
b10010 :
b11 J
b10 I
b10 $
b10 3
b10 G
b10 Y
1*
1/
#280000
0*
0/
#290000
b110 Z
b110 )
b110 :
b100 J
b11 I
b11 $
b11 3
b11 G
b11 Y
1*
1/
#300000
0*
0/
#310000
b1001100 Z
b1001100 )
b1001100 :
b101 J
b100 I
b100 $
b100 3
b100 G
b100 Y
1*
1/
#320000
0*
0/
#330000
b100100 Z
b100100 )
b100100 :
b110 J
b101 I
b101 $
b101 3
b101 G
b101 Y
1*
1/
#340000
0*
0/
#350000
b100000 Z
b100000 )
b100000 :
b111 J
b110 I
b110 $
b110 3
b110 G
b110 Y
1*
1/
#360000
0*
0/
#370000
b1111 Z
b1111 )
b1111 :
b1000 J
b111 I
b111 $
b111 3
b111 G
b111 Y
1*
1/
#380000
0*
0/
#390000
b0 Z
b0 )
b0 :
b1001 J
b1000 I
b1000 $
b1000 3
b1000 G
b1000 Y
1*
1/
#400000
0*
0/
#410000
1=
1H
b100 Z
b100 )
b100 :
b0 J
b1001 I
b1001 $
b1001 3
b1001 G
b1001 Y
1*
1/
#420000
0*
0/
#430000
0=
0H
b110 X
b110 (
b110 9
b100 L
b1 Z
b1 )
b1 :
b1 J
b11 K
b11 #
b11 2
b11 E
b11 W
b0 I
b0 $
b0 3
b0 G
b0 Y
1*
1/
#440000
0*
0/
#450000
b1001111 Z
b1001111 )
b1001111 :
b10 J
b1 I
b1 $
b1 3
b1 G
b1 Y
1*
1/
#460000
0*
0/
#470000
b10010 Z
b10010 )
b10010 :
b11 J
b10 I
b10 $
b10 3
b10 G
b10 Y
1*
1/
#480000
0*
0/
#490000
b110 Z
b110 )
b110 :
b100 J
b11 I
b11 $
b11 3
b11 G
b11 Y
1*
1/
#500000
0*
0/
#510000
b1001100 Z
b1001100 )
b1001100 :
b101 J
b100 I
b100 $
b100 3
b100 G
b100 Y
1*
1/
#520000
0*
0/
#530000
b100100 Z
b100100 )
b100100 :
b110 J
b101 I
b101 $
b101 3
b101 G
b101 Y
1*
1/
#540000
0*
0/
#550000
b100000 Z
b100000 )
b100000 :
b111 J
b110 I
b110 $
b110 3
b110 G
b110 Y
1*
1/
#560000
0*
0/
#570000
b1111 Z
b1111 )
b1111 :
b1000 J
b111 I
b111 $
b111 3
b111 G
b111 Y
1*
1/
#580000
0*
0/
#590000
b0 Z
b0 )
b0 :
b1001 J
b1000 I
b1000 $
b1000 3
b1000 G
b1000 Y
1*
1/
#600000
0*
0/
#610000
1=
1H
b100 Z
b100 )
b100 :
b0 J
b1001 I
b1001 $
b1001 3
b1001 G
b1001 Y
1*
1/
#620000
0*
0/
#630000
0=
0H
b1001100 X
b1001100 (
b1001100 9
b101 L
b1 Z
b1 )
b1 :
b1 J
b100 K
b100 #
b100 2
b100 E
b100 W
b0 I
b0 $
b0 3
b0 G
b0 Y
1*
1/
#640000
0*
0/
#650000
b1001111 Z
b1001111 )
b1001111 :
b10 J
b1 I
b1 $
b1 3
b1 G
b1 Y
1*
1/
#660000
0*
0/
#670000
b10010 Z
b10010 )
b10010 :
b11 J
b10 I
b10 $
b10 3
b10 G
b10 Y
1*
1/
#680000
0*
0/
#690000
b110 Z
b110 )
b110 :
b100 J
b11 I
b11 $
b11 3
b11 G
b11 Y
1*
1/
#700000
0*
0/
#710000
b1001100 Z
b1001100 )
b1001100 :
b101 J
b100 I
b100 $
b100 3
b100 G
b100 Y
1*
1/
#720000
0*
0/
#730000
b100100 Z
b100100 )
b100100 :
b110 J
b101 I
b101 $
b101 3
b101 G
b101 Y
1*
1/
#740000
0*
0/
#750000
b100000 Z
b100000 )
b100000 :
b111 J
b110 I
b110 $
b110 3
b110 G
b110 Y
1*
1/
#760000
0*
0/
#770000
b1111 Z
b1111 )
b1111 :
b1000 J
b111 I
b111 $
b111 3
b111 G
b111 Y
1*
1/
#780000
0*
0/
#790000
b0 Z
b0 )
b0 :
b1001 J
b1000 I
b1000 $
b1000 3
b1000 G
b1000 Y
1*
1/
#800000
0*
0/
#810000
1=
1H
b100 Z
b100 )
b100 :
b0 J
b1001 I
b1001 $
b1001 3
b1001 G
b1001 Y
1*
1/
#820000
0*
0/
#830000
0=
0H
b100100 X
b100100 (
b100100 9
b110 L
b1 Z
b1 )
b1 :
b1 J
b101 K
b101 #
b101 2
b101 E
b101 W
b0 I
b0 $
b0 3
b0 G
b0 Y
1*
1/
#840000
0*
0/
#850000
b1001111 Z
b1001111 )
b1001111 :
b10 J
b1 I
b1 $
b1 3
b1 G
b1 Y
1*
1/
#860000
0*
0/
#870000
b10010 Z
b10010 )
b10010 :
b11 J
b10 I
b10 $
b10 3
b10 G
b10 Y
1*
1/
#880000
0*
0/
#890000
b110 Z
b110 )
b110 :
b100 J
b11 I
b11 $
b11 3
b11 G
b11 Y
1*
1/
#900000
0*
0/
#910000
b1001100 Z
b1001100 )
b1001100 :
b101 J
b100 I
b100 $
b100 3
b100 G
b100 Y
1*
1/
#920000
0*
0/
#930000
b100100 Z
b100100 )
b100100 :
b110 J
b101 I
b101 $
b101 3
b101 G
b101 Y
1*
1/
#940000
0*
0/
#950000
b100000 Z
b100000 )
b100000 :
b111 J
b110 I
b110 $
b110 3
b110 G
b110 Y
1*
1/
#960000
0*
0/
#970000
b1111 Z
b1111 )
b1111 :
b1000 J
b111 I
b111 $
b111 3
b111 G
b111 Y
1*
1/
#980000
0*
0/
#990000
b0 Z
b0 )
b0 :
b1001 J
b1000 I
b1000 $
b1000 3
b1000 G
b1000 Y
1*
1/
#1000000
0*
0/
#1010000
1=
1H
b100 Z
b100 )
b100 :
b0 J
b1001 I
b1001 $
b1001 3
b1001 G
b1001 Y
1*
1/
#1020000
0*
0/
#1030000
0=
0H
b100000 X
b100000 (
b100000 9
b111 L
b1 Z
b1 )
b1 :
b1 J
b110 K
b110 #
b110 2
b110 E
b110 W
b0 I
b0 $
b0 3
b0 G
b0 Y
1*
1/
#1040000
0*
0/
#1050000
b1001111 Z
b1001111 )
b1001111 :
b10 J
b1 I
b1 $
b1 3
b1 G
b1 Y
1*
1/
#1060000
0*
0/
#1070000
b10010 Z
b10010 )
b10010 :
b11 J
b10 I
b10 $
b10 3
b10 G
b10 Y
1*
1/
#1080000
0*
0/
#1090000
b110 Z
b110 )
b110 :
b100 J
b11 I
b11 $
b11 3
b11 G
b11 Y
1*
1/
#1100000
0*
0/
#1110000
b1001100 Z
b1001100 )
b1001100 :
b101 J
b100 I
b100 $
b100 3
b100 G
b100 Y
1*
1/
#1120000
0*
0/
#1130000
b100100 Z
b100100 )
b100100 :
b110 J
b101 I
b101 $
b101 3
b101 G
b101 Y
1*
1/
#1140000
0*
0/
#1150000
b100000 Z
b100000 )
b100000 :
b111 J
b110 I
b110 $
b110 3
b110 G
b110 Y
1*
1/
#1160000
0*
0/
#1170000
b1111 Z
b1111 )
b1111 :
b1000 J
b111 I
b111 $
b111 3
b111 G
b111 Y
1*
1/
#1180000
0*
0/
#1190000
b0 Z
b0 )
b0 :
b1001 J
b1000 I
b1000 $
b1000 3
b1000 G
b1000 Y
1*
1/
#1200000
0*
0/
#1210000
1=
1H
b100 Z
b100 )
b100 :
b0 J
b1001 I
b1001 $
b1001 3
b1001 G
b1001 Y
1*
1/
#1220000
0*
0/
#1230000
0=
0H
b1111 X
b1111 (
b1111 9
b1000 L
b1 Z
b1 )
b1 :
b1 J
b111 K
b111 #
b111 2
b111 E
b111 W
b0 I
b0 $
b0 3
b0 G
b0 Y
1*
1/
#1240000
0*
0/
#1250000
b1001111 Z
b1001111 )
b1001111 :
b10 J
b1 I
b1 $
b1 3
b1 G
b1 Y
1*
1/
#1260000
0*
0/
#1270000
b10010 Z
b10010 )
b10010 :
b11 J
b10 I
b10 $
b10 3
b10 G
b10 Y
1*
1/
#1280000
0*
0/
#1290000
b110 Z
b110 )
b110 :
b100 J
b11 I
b11 $
b11 3
b11 G
b11 Y
1*
1/
#1300000
0*
0/
#1310000
b1001100 Z
b1001100 )
b1001100 :
b101 J
b100 I
b100 $
b100 3
b100 G
b100 Y
1*
1/
#1320000
0*
0/
#1330000
b100100 Z
b100100 )
b100100 :
b110 J
b101 I
b101 $
b101 3
b101 G
b101 Y
1*
1/
#1340000
0*
0/
#1350000
b100000 Z
b100000 )
b100000 :
b111 J
b110 I
b110 $
b110 3
b110 G
b110 Y
1*
1/
#1360000
0*
0/
#1370000
b1111 Z
b1111 )
b1111 :
b1000 J
b111 I
b111 $
b111 3
b111 G
b111 Y
1*
1/
#1380000
0*
0/
#1390000
b0 Z
b0 )
b0 :
b1001 J
b1000 I
b1000 $
b1000 3
b1000 G
b1000 Y
1*
1/
#1400000
0*
0/
#1410000
1=
1H
b100 Z
b100 )
b100 :
b0 J
b1001 I
b1001 $
b1001 3
b1001 G
b1001 Y
1*
1/
#1420000
0*
0/
#1430000
0=
0H
b0 X
b0 (
b0 9
b1001 L
b1 Z
b1 )
b1 :
b1 J
b1000 K
b1000 #
b1000 2
b1000 E
b1000 W
b0 I
b0 $
b0 3
b0 G
b0 Y
1*
1/
#1440000
0*
0/
#1450000
b1001111 Z
b1001111 )
b1001111 :
b10 J
b1 I
b1 $
b1 3
b1 G
b1 Y
1*
1/
#1460000
0*
0/
#1470000
b10010 Z
b10010 )
b10010 :
b11 J
b10 I
b10 $
b10 3
b10 G
b10 Y
1*
1/
#1480000
0*
0/
#1490000
b110 Z
b110 )
b110 :
b100 J
b11 I
b11 $
b11 3
b11 G
b11 Y
1*
1/
#1500000
0*
0/
#1510000
b1001100 Z
b1001100 )
b1001100 :
b101 J
b100 I
b100 $
b100 3
b100 G
b100 Y
1*
1/
#1520000
0*
0/
#1530000
b100100 Z
b100100 )
b100100 :
b110 J
b101 I
b101 $
b101 3
b101 G
b101 Y
1*
1/
#1540000
0*
0/
#1550000
b100000 Z
b100000 )
b100000 :
b111 J
b110 I
b110 $
b110 3
b110 G
b110 Y
1*
1/
#1560000
0*
0/
#1570000
b1111 Z
b1111 )
b1111 :
b1000 J
b111 I
b111 $
b111 3
b111 G
b111 Y
1*
1/
#1580000
0*
0/
#1590000
b0 Z
b0 )
b0 :
b1001 J
b1000 I
b1000 $
b1000 3
b1000 G
b1000 Y
1*
1/
#1600000
0*
0/
#1610000
1=
1H
b100 Z
b100 )
b100 :
b0 J
b1001 I
b1001 $
b1001 3
b1001 G
b1001 Y
1*
1/
#1620000
0*
0/
#1630000
0C
0=
0D
0H
b100 X
b100 (
b100 9
b0 L
b1 Z
b1 )
b1 :
b1 J
b1001 K
b1001 #
b1001 2
b1001 E
b1001 W
b0 I
b0 $
b0 3
b0 G
b0 Y
1*
1/
#1640000
0*
0/
#1650000
b1001111 Z
b1001111 )
b1001111 :
b10 J
b1 I
b1 $
b1 3
b1 G
b1 Y
1*
1/
#1660000
0*
0/
#1670000
b10010 Z
b10010 )
b10010 :
b11 J
b10 I
b10 $
b10 3
b10 G
b10 Y
1*
1/
#1680000
0*
0/
#1690000
b110 Z
b110 )
b110 :
b100 J
b11 I
b11 $
b11 3
b11 G
b11 Y
1*
1/
#1700000
0*
0/
#1710000
b1001100 Z
b1001100 )
b1001100 :
b101 J
b100 I
b100 $
b100 3
b100 G
b100 Y
1*
1/
#1720000
0*
0/
#1730000
b100100 Z
b100100 )
b100100 :
b110 J
b101 I
b101 $
b101 3
b101 G
b101 Y
1*
1/
#1740000
0*
0/
#1750000
b100000 Z
b100000 )
b100000 :
b111 J
b110 I
b110 $
b110 3
b110 G
b110 Y
1*
1/
#1760000
0*
0/
#1770000
b1111 Z
b1111 )
b1111 :
b1000 J
b111 I
b111 $
b111 3
b111 G
b111 Y
1*
1/
#1780000
0*
0/
#1790000
b0 Z
b0 )
b0 :
b1001 J
b1000 I
b1000 $
b1000 3
b1000 G
b1000 Y
1*
1/
#1800000
0*
0/
#1810000
1C
1D
1=
1H
b100 Z
b100 )
b100 :
b0 J
b1001 I
b1001 $
b1001 3
b1001 G
b1001 Y
1*
1/
#1820000
0*
0/
#1830000
0C
0=
0D
0H
b10010 V
b10010 '
b10010 8
b11 N
b1 X
b1 (
b1 9
b1 L
b1 Z
b1 )
b1 :
b1 J
b10 M
b10 "
b10 1
b10 F
b10 U
b0 K
b0 #
b0 2
b0 E
b0 W
b0 I
b0 $
b0 3
b0 G
b0 Y
1*
1/
#1840000
0*
0/
#1850000
b1001111 Z
b1001111 )
b1001111 :
b10 J
b1 I
b1 $
b1 3
b1 G
b1 Y
1*
1/
#1860000
0*
0/
#1870000
b10010 Z
b10010 )
b10010 :
b11 J
b10 I
b10 $
b10 3
b10 G
b10 Y
1*
1/
#1880000
0*
0/
#1890000
b110 Z
b110 )
b110 :
b100 J
b11 I
b11 $
b11 3
b11 G
b11 Y
1*
1/
#1900000
0*
0/
#1910000
b1001100 Z
b1001100 )
b1001100 :
b101 J
b100 I
b100 $
b100 3
b100 G
b100 Y
1*
1/
#1920000
0*
0/
#1930000
b100100 Z
b100100 )
b100100 :
b110 J
b101 I
b101 $
b101 3
b101 G
b101 Y
1*
1/
#1940000
0*
0/
#1950000
b100000 Z
b100000 )
b100000 :
b111 J
b110 I
b110 $
b110 3
b110 G
b110 Y
1*
1/
#1960000
0*
0/
#1970000
b1111 Z
b1111 )
b1111 :
b1000 J
b111 I
b111 $
b111 3
b111 G
b111 Y
1*
1/
#1980000
0*
0/
#1990000
b0 Z
b0 )
b0 :
b1001 J
b1000 I
b1000 $
b1000 3
b1000 G
b1000 Y
1*
1/
#2000000
0*
0/
#2010000
1=
1H
b100 Z
b100 )
b100 :
b0 J
b1001 I
b1001 $
b1001 3
b1001 G
b1001 Y
1*
1/
#2020000
0*
0/
#2030000
0=
0H
b1001111 X
b1001111 (
b1001111 9
b10 L
b1 Z
b1 )
b1 :
b1 J
b1 K
b1 #
b1 2
b1 E
b1 W
b0 I
b0 $
b0 3
b0 G
b0 Y
1*
1/
#2040000
0*
0/
#2050000
b1001111 Z
b1001111 )
b1001111 :
b10 J
b1 I
b1 $
b1 3
b1 G
b1 Y
1*
1/
#2060000
0*
0/
#2070000
b10010 Z
b10010 )
b10010 :
b11 J
b10 I
b10 $
b10 3
b10 G
b10 Y
1*
1/
#2080000
0*
0/
#2090000
b110 Z
b110 )
b110 :
b100 J
b11 I
b11 $
b11 3
b11 G
b11 Y
1*
1/
#2100000
0*
0/
#2110000
b1001100 Z
b1001100 )
b1001100 :
b101 J
b100 I
b100 $
b100 3
b100 G
b100 Y
1*
1/
#2120000
0*
0/
#2130000
b100100 Z
b100100 )
b100100 :
b110 J
b101 I
b101 $
b101 3
b101 G
b101 Y
1*
1/
#2140000
0*
0/
#2150000
b100000 Z
b100000 )
b100000 :
b111 J
b110 I
b110 $
b110 3
b110 G
b110 Y
1*
1/
#2160000
0*
0/
#2170000
b1111 Z
b1111 )
b1111 :
b1000 J
b111 I
b111 $
b111 3
b111 G
b111 Y
1*
1/
#2180000
0*
0/
#2190000
b0 Z
b0 )
b0 :
b1001 J
b1000 I
b1000 $
b1000 3
b1000 G
b1000 Y
1*
1/
#2200000
0*
0/
#2210000
1=
1H
b100 Z
b100 )
b100 :
b0 J
b1001 I
b1001 $
b1001 3
b1001 G
b1001 Y
1*
1/
#2220000
0*
0/
#2230000
0=
0H
b10010 X
b10010 (
b10010 9
b11 L
b1 Z
b1 )
b1 :
b1 J
b10 K
b10 #
b10 2
b10 E
b10 W
b0 I
b0 $
b0 3
b0 G
b0 Y
1*
1/
#2240000
0*
0/
#2250000
b1001111 Z
b1001111 )
b1001111 :
b10 J
b1 I
b1 $
b1 3
b1 G
b1 Y
1*
1/
#2260000
0*
0/
#2270000
b10010 Z
b10010 )
b10010 :
b11 J
b10 I
b10 $
b10 3
b10 G
b10 Y
1*
1/
#2280000
0*
0/
#2290000
b110 Z
b110 )
b110 :
b100 J
b11 I
b11 $
b11 3
b11 G
b11 Y
1*
1/
#2300000
0*
0/
#2310000
b1001100 Z
b1001100 )
b1001100 :
b101 J
b100 I
b100 $
b100 3
b100 G
b100 Y
1*
1/
#2320000
0*
0/
#2330000
b100100 Z
b100100 )
b100100 :
b110 J
b101 I
b101 $
b101 3
b101 G
b101 Y
1*
1/
#2340000
0*
0/
#2350000
b100000 Z
b100000 )
b100000 :
b111 J
b110 I
b110 $
b110 3
b110 G
b110 Y
1*
1/
#2360000
0*
0/
#2370000
b1111 Z
b1111 )
b1111 :
b1000 J
b111 I
b111 $
b111 3
b111 G
b111 Y
1*
1/
#2380000
0*
0/
#2390000
b0 Z
b0 )
b0 :
b1001 J
b1000 I
b1000 $
b1000 3
b1000 G
b1000 Y
1*
1/
#2400000
0*
0/
#2410000
1=
1H
b100 Z
b100 )
b100 :
b0 J
b1001 I
b1001 $
b1001 3
b1001 G
b1001 Y
1*
1/
#2420000
0*
0/
#2430000
0=
0H
b110 X
b110 (
b110 9
b100 L
b1 Z
b1 )
b1 :
b1 J
b11 K
b11 #
b11 2
b11 E
b11 W
b0 I
b0 $
b0 3
b0 G
b0 Y
1*
1/
#2440000
0*
0/
#2450000
b1001111 Z
b1001111 )
b1001111 :
b10 J
b1 I
b1 $
b1 3
b1 G
b1 Y
1*
1/
#2460000
0*
0/
#2470000
b10010 Z
b10010 )
b10010 :
b11 J
b10 I
b10 $
b10 3
b10 G
b10 Y
1*
1/
#2480000
0*
0/
#2490000
b110 Z
b110 )
b110 :
b100 J
b11 I
b11 $
b11 3
b11 G
b11 Y
1*
1/
#2500000
0*
0/
#2510000
b1001100 Z
b1001100 )
b1001100 :
b101 J
b100 I
b100 $
b100 3
b100 G
b100 Y
1*
1/
#2520000
0*
0/
#2530000
b100100 Z
b100100 )
b100100 :
b110 J
b101 I
b101 $
b101 3
b101 G
b101 Y
1*
1/
#2540000
0*
0/
#2550000
b100000 Z
b100000 )
b100000 :
b111 J
b110 I
b110 $
b110 3
b110 G
b110 Y
1*
1/
#2560000
0*
0/
#2570000
b1111 Z
b1111 )
b1111 :
b1000 J
b111 I
b111 $
b111 3
b111 G
b111 Y
1*
1/
#2580000
0*
0/
#2590000
b0 Z
b0 )
b0 :
b1001 J
b1000 I
b1000 $
b1000 3
b1000 G
b1000 Y
1*
1/
#2600000
0*
0/
#2610000
1=
1H
b100 Z
b100 )
b100 :
b0 J
b1001 I
b1001 $
b1001 3
b1001 G
b1001 Y
1*
1/
#2620000
0*
0/
#2630000
0=
0H
b1001100 X
b1001100 (
b1001100 9
b101 L
b1 Z
b1 )
b1 :
b1 J
b100 K
b100 #
b100 2
b100 E
b100 W
b0 I
b0 $
b0 3
b0 G
b0 Y
1*
1/
#2640000
0*
0/
#2650000
b1001111 Z
b1001111 )
b1001111 :
b10 J
b1 I
b1 $
b1 3
b1 G
b1 Y
1*
1/
#2660000
0*
0/
#2670000
b10010 Z
b10010 )
b10010 :
b11 J
b10 I
b10 $
b10 3
b10 G
b10 Y
1*
1/
#2680000
0*
0/
#2690000
b110 Z
b110 )
b110 :
b100 J
b11 I
b11 $
b11 3
b11 G
b11 Y
1*
1/
#2700000
0*
0/
#2710000
b1001100 Z
b1001100 )
b1001100 :
b101 J
b100 I
b100 $
b100 3
b100 G
b100 Y
1*
1/
#2720000
0*
0/
